impulse_core/__init__.py
impulse_core/logger.py
impulse_core/schema.py
impulse_core/tracer.py
impulse_core-0.1.6.dist-info/LICENSE
impulse_core-0.1.6.dist-info/METADATA
impulse_core-0.1.6.dist-info/WHEEL
impulse_core-0.1.6.dist-info/RECORD
