Metadata-Version: 2.1
Name: impulse-core
Version: 0.1.6
Summary: 
Home-page: https://github.com/sudowoodo200/impulse-core/
Author: sudowoodo200
Author-email: sudowoodo200@gmail.com
Requires-Python: >=3.9,<4.0
Classifier: Programming Language :: Python :: 3
Classifier: Programming Language :: Python :: 3.9
Classifier: Programming Language :: Python :: 3.10
Classifier: Programming Language :: Python :: 3.11
Requires-Dist: pydantic (>=1.10.5,<2.0.0)
Requires-Dist: pymongo (>=4.3.3,<5.0.0)
Requires-Dist: typing-extensions (>=4.7.1,<5.0.0)
Project-URL: Repository, https://github.com/sudowoodo200/impulse-core/
